ColorizeText/__init__.py
ColorizeText/color_text.py
ColorizeText-0.1.2.dist-info/LICENCE
ColorizeText-0.1.2.dist-info/METADATA
ColorizeText-0.1.2.dist-info/WHEEL
ColorizeText-0.1.2.dist-info/top_level.txt
ColorizeText-0.1.2.dist-info/RECORD
