Metadata-Version: 2.2
Name: ColorizeText
Version: 0.1.2
Summary: Un package simple pour colorer les textes dans la console
Home-page: https://github.com/Uwu-Kagami
Author: Kagami
Classifier: Programming Language :: Python :: 3
Classifier: License :: OSI Approved :: MIT License
Classifier: Operating System :: OS Independent
Requires-Python: >=3.6
License-File: LICENCE
Dynamic: author
Dynamic: classifier
Dynamic: description
Dynamic: description-content-type
Dynamic: home-page
Dynamic: requires-python
Dynamic: summary
